{"trial_id": "0025", "hyperparameters": {"space": [{"class_name": "Choice", "config": {"name": "units", "default": 64, "conditions": [], "values": [64, 128, 256], "ordered": true}}, {"class_name": "Choice", "config": {"name": "activation", "default": "sigmoid", "conditions": [], "values": ["sigmoid", "relu", "tanh"], "ordered": false}}, {"class_name": "Choice", "config": {"name": "init", "default": "glorot_uniform", "conditions": [], "values": ["glorot_uniform", "glorot_normal", "random_normal"], "ordered": false}}, {"class_name": "Choice", "config": {"name": "optimizer", "default": "adam", "conditions": [], "values": ["adam", "sgd", "rmsprop"], "ordered": false}}, {"class_name": "Choice", "config": {"name": "loss", "default": "categorical_crossentropy", "conditions": [], "values": ["categorical_crossentropy", "mse", "mae"], "ordered": false}}], "values": {"units": 64, "activation": "sigmoid", "init": "random_normal", "optimizer": "rmsprop", "loss": "mse"}}, "metrics": {"metrics": {"loss": {"direction": "min", "observations": [{"value": [0.013555780053138733], "step": 98}]}, "accuracy": {"direction": "max", "observations": [{"value": [0.9125312566757202], "step": 98}]}, "val_loss": {"direction": "min", "observations": [{"value": [0.015595867298543453], "step": 98}]}, "val_accuracy": {"direction": "max", "observations": [{"value": [0.8934999704360962], "step": 98}]}}}, "score": 0.8934999704360962, "best_step": 98, "status": "COMPLETED", "message": null}